cfgen/__init__.py
cfgen/cfgen.py
cfgen-0.2.5.data/scripts/cfgen
cfgen-0.2.5.dist-info/top_level.txt
cfgen-0.2.5.dist-info/METADATA
cfgen-0.2.5.dist-info/DESCRIPTION.rst
cfgen-0.2.5.dist-info/metadata.json
cfgen-0.2.5.dist-info/WHEEL
cfgen-0.2.5.dist-info/RECORD
