Metadata-Version: 2.0
Name: cfgen
Version: 0.2.5
Summary: Configuration tool for configuration files
Home-page: https://github.com/rzhilkibaev/cfgen
Author: Renat Zhilkibaev
Author-email: rzhilkibaev@gmail.com
License: MIT
Platform: UNKNOWN
Classifier: Development Status :: 3 - Alpha
Classifier: Environment :: Console
Classifier: Intended Audience :: Developers
Classifier: License :: OSI Approved :: MIT License
Classifier: Natural Language :: English
Classifier: Operating System :: POSIX :: Linux
Classifier: Programming Language :: Python :: 2.7
Classifier: Topic :: Utilities
Requires-Dist: docopt
Requires-Dist: future
Requires-Dist: jinja2
